lda4microbiome/__init__.py
lda4microbiome/metrics.py
lda4microbiome/preprocessing.py
lda4microbiome/selection.py
lda4microbiome/stripesankey.py
lda4microbiome/training.py
lda4microbiome/visualization.py
lda4microbiome-0.1.21.dist-info/licenses/LICENSE
lda4microbiome-0.1.21.dist-info/METADATA
lda4microbiome-0.1.21.dist-info/WHEEL
lda4microbiome-0.1.21.dist-info/top_level.txt
lda4microbiome-0.1.21.dist-info/RECORD
