Metadata-Version: 2.4
Name: lda4microbiome
Version: 0.1.21
Summary: A workflow for LDA analysis of microbiome data using MALLET with interactive Sankey visualizations
Home-page: https://gitlab.kuleuven.be/aida-lab/projects/LDA4Microbiome_Workflow
Author: Peiyang Huo
Author-email: peiyang.huo@kuleuven.be
Classifier: Programming Language :: Python
Classifier: License :: OSI Approved :: MIT License
Classifier: Operating System :: OS Independent
Requires-Python: >=3.7
License-File: LICENSE
Requires-Dist: pandas
Requires-Dist: numpy
Requires-Dist: matplotlib
Requires-Dist: seaborn
Requires-Dist: gensim
Requires-Dist: little-mallet-wrapper
Requires-Dist: plotly>=5.0.0
Requires-Dist: scipy
Requires-Dist: anywidget
Requires-Dist: traitlets
Dynamic: author
Dynamic: author-email
Dynamic: classifier
Dynamic: description
Dynamic: description-content-type
Dynamic: home-page
Dynamic: license-file
Dynamic: requires-dist
Dynamic: requires-python
Dynamic: summary
